file_summarizer/__init__.py
file_summarizer/file_summarizer.py
file_summarizer_mcp_server-0.1.1.dist-info/METADATA
file_summarizer_mcp_server-0.1.1.dist-info/WHEEL
file_summarizer_mcp_server-0.1.1.dist-info/entry_points.txt
file_summarizer_mcp_server-0.1.1.dist-info/licenses/LICENSE
file_summarizer_mcp_server-0.1.1.dist-info/RECORD
