Metadata-Version: 2.4
Name: file-summarizer-mcp-server
Version: 0.1.1
Summary: A Model Context Protocol (MCP) server for reading and summarizing file content with language support
Author-email: Muskan Raghav <raghav12muskan@gmail.com>
License: MIT
License-File: LICENSE
Requires-Python: >=3.12
Requires-Dist: deep-translator
Requires-Dist: fastmcp
Requires-Dist: httpx
Requires-Dist: langdetect
Requires-Dist: openai-whisper
Requires-Dist: tika
Requires-Dist: whisper
